whiteCalculator/ERRORS.py
whiteCalculator/Formula.py
whiteCalculator/__init__.py
whiteCalculator/calculator.py
whiteCalculator/maths.py
whiteCalculator/timeout.py
whiteCalculator-0.0.10.dist-info/LICENSE
whiteCalculator-0.0.10.dist-info/METADATA
whiteCalculator-0.0.10.dist-info/WHEEL
whiteCalculator-0.0.10.dist-info/top_level.txt
whiteCalculator-0.0.10.dist-info/RECORD
