Metadata-Version: 2.1
Name: whiteCalculator
Version: 0.0.10
Summary: A small calculator module for Python
Home-page: https://github.com/WhiteNightAWA/whiteCalculator
Author: WhiteNight
Author-email: evan.tang.2021@gmail.com
License: MIT License
Project-URL: Home Page, https://whitenightawa.github.io/whiteCalculator/
Project-URL: Bug Tracker, https://github.com/WhiteNightAWA/whiteCalculator/issues
Project-URL: Documentation, https://whitenightawa.github.io/whiteCalculator/DOCS/
Project-URL: Funding, https://www.buymeacoffee.com/WhiteNightAWA
Classifier: Programming Language :: Python :: 3
Classifier: License :: OSI Approved :: MIT License
Requires-Python: >=3.6
License-File: LICENSE
